gocept.reference-1.0-py3.11-nspkg.pth
gocept/reference/__init__.py
gocept/reference/collection.py
gocept/reference/collection.txt
gocept/reference/configure.zcml
gocept/reference/content.py
gocept/reference/field.py
gocept/reference/field.txt
gocept/reference/fix.py
gocept/reference/fix.txt
gocept/reference/ftesting.zcml
gocept/reference/interfaces.py
gocept/reference/manager.py
gocept/reference/reference.py
gocept/reference/reference.txt
gocept/reference/regression.txt
gocept/reference/testing.py
gocept/reference/verify.py
gocept/reference/verify.txt
gocept/reference/generations/__init__.py
gocept/reference/generations/evolve1.py
gocept/reference/generations/evolve2.py
gocept/reference/generations/install.py
gocept/reference/tests/__init__.py
gocept/reference/tests/test_doctests.py
gocept/reference/tests/test_fix.py
gocept.reference-1.0.dist-info/LICENSE.txt
gocept.reference-1.0.dist-info/METADATA
gocept.reference-1.0.dist-info/WHEEL
gocept.reference-1.0.dist-info/namespace_packages.txt
gocept.reference-1.0.dist-info/top_level.txt
gocept.reference-1.0.dist-info/RECORD
