Metadata-Version: 2.1
Name: gocept.reference
Version: 1.0
Summary: Intrinsic references for Zope/ZODB applications.
Home-page: https://github.com/gocept/gocept.reference
Author: gocept gmbh & co. kg
Author-email: mail@gocept.com
License: ZPL 2.1
Keywords: zodb zope3 intrinsic reference
Classifier: Topic :: Software Development
Classifier: Topic :: Database
Classifier: Framework :: ZODB
Classifier: Framework :: Zope :: 3
Classifier: Development Status :: 4 - Beta
Classifier: Intended Audience :: Developers
Classifier: License :: OSI Approved
Classifier: Programming Language :: Python :: 3
Classifier: Programming Language :: Python :: 3.7
Classifier: Programming Language :: Python :: 3.8
Classifier: Programming Language :: Python :: 3.9
Classifier: Programming Language :: Python :: 3.10
Classifier: Programming Language :: Python :: 3.11
Classifier: License :: OSI Approved :: Zope Public License
Classifier: Natural Language :: English
Classifier: Operating System :: OS Independent
Classifier: Programming Language :: Python
Requires-Python: >=3.7
License-File: LICENSE.txt
Requires-Dist: BTrees
Requires-Dist: ZODB
Requires-Dist: persistent
Requires-Dist: setuptools
Requires-Dist: transaction
Requires-Dist: zope.annotation
Requires-Dist: zope.component
Requires-Dist: zope.container
Requires-Dist: zope.deferredimport
Requires-Dist: zope.generations
Requires-Dist: zope.interface
Requires-Dist: zope.location
Requires-Dist: zope.schema (>=3.6.0)
Requires-Dist: zope.traversing
Provides-Extra: test
Requires-Dist: zope.app.testing ; extra == 'test'
Requires-Dist: zope.app.zcmlfiles ; extra == 'test'
Requires-Dist: gocept.pytestlayer ; extra == 'test'
